tensor_regression/__init__.py
tensor_regression/fixture.py
tensor_regression/flatten.py
tensor_regression/pytest_plugin.py
tensor_regression/stats.py
tensor_regression/to_array.py
tensor_regression-0.1.1.dist-info/METADATA
tensor_regression-0.1.1.dist-info/WHEEL
tensor_regression-0.1.1.dist-info/entry_points.txt
tensor_regression-0.1.1.dist-info/licenses/LICENSE
tensor_regression-0.1.1.dist-info/RECORD
