Metadata-Version: 2.4
Name: tensor-regression
Version: 0.1.1
Summary: A small wrapper around pytest_regressions for Tensors
Author-email: Fabrice Normandin <fabrice.normandin@gmail.com>
License-Expression: MIT
License-File: LICENSE
Classifier: Development Status :: 4 - Beta
Classifier: Framework :: Pytest
Classifier: Intended Audience :: Developers
Classifier: License :: OSI Approved :: MIT License
Classifier: Natural Language :: English
Classifier: Programming Language :: Python :: 3.10
Classifier: Programming Language :: Python :: 3.11
Classifier: Programming Language :: Python :: 3.12
Classifier: Topic :: Software Development :: Libraries
Requires-Python: >=3.10
Requires-Dist: numpy>=1.26.4
Requires-Dist: optree>=0.15.0
Requires-Dist: pytest-regressions>=2.5.0
